redturtle.faq-1.0.2-py3.10-nspkg.pth
redturtle/faq/__init__.py
redturtle/faq/configure.zcml
redturtle/faq/content.py
redturtle/faq/interfaces.py
redturtle/faq/permissions.zcml
redturtle/faq/setuphandlers.py
redturtle/faq/testing.py
redturtle/faq/browser/__init__.py
redturtle/faq/browser/configure.zcml
redturtle/faq/browser/overrides/.gitkeep
redturtle/faq/browser/static/.gitkeep
redturtle/faq/locales/README.rst
redturtle/faq/locales/__init__.py
redturtle/faq/locales/redturtle.faq.pot
redturtle/faq/locales/update.py
redturtle/faq/locales/update.sh
redturtle/faq/locales/__pycache__/LC_MESSAGES/redturtle.faq.mo
redturtle/faq/locales/__pycache__/LC_MESSAGES/redturtle.faq.po
redturtle/faq/locales/it/LC_MESSAGES/redturtle.faq.mo
redturtle/faq/locales/it/LC_MESSAGES/redturtle.faq.po
redturtle/faq/profiles/default/browserlayer.xml
redturtle/faq/profiles/default/catalog.xml
redturtle/faq/profiles/default/metadata.xml
redturtle/faq/profiles/default/rolemap.xml
redturtle/faq/profiles/default/types.xml
redturtle/faq/profiles/default/registry/main.xml
redturtle/faq/profiles/default/types/Faq.xml
redturtle/faq/profiles/default/types/FaqFolder.xml
redturtle/faq/profiles/uninstall/browserlayer.xml
redturtle/faq/restapi/__init__.py
redturtle/faq/restapi/configure.zcml
redturtle/faq/restapi/serializers/__init__.py
redturtle/faq/restapi/serializers/configure.zcml
redturtle/faq/restapi/serializers/serializer.py
redturtle/faq/restapi/services/__init__.py
redturtle/faq/restapi/services/configure.zcml
redturtle/faq/restapi/services/faq_structure.py
redturtle/faq/tests/__init__.py
redturtle/faq/tests/test_ct.py
redturtle/faq/tests/test_faq_structure_expandable.py
redturtle/faq/tests/test_setup.py
redturtle.faq-1.0.2.dist-info/LICENSE.GPL
redturtle.faq-1.0.2.dist-info/LICENSE.rst
redturtle.faq-1.0.2.dist-info/METADATA
redturtle.faq-1.0.2.dist-info/WHEEL
redturtle.faq-1.0.2.dist-info/entry_points.txt
redturtle.faq-1.0.2.dist-info/namespace_packages.txt
redturtle.faq-1.0.2.dist-info/top_level.txt
redturtle.faq-1.0.2.dist-info/RECORD
